setup.py
pyroclast/LICENSE.txt
pyroclast/README.md
pyroclast/__init__.py
pyroclast/basic.py
pyroclast/dataTables.py
pyroclast/objectHierarchies.py
pyroclast/server.py
pyroclast.egg-info/PKG-INFO
pyroclast.egg-info/SOURCES.txt
pyroclast.egg-info/dependency_links.txt
pyroclast.egg-info/requires.txt
pyroclast.egg-info/top_level.txt
pyroclast/data/__init__.py
pyroclast/data/country_data.json
pyroclast/data/test.csv
pyroclast/data/test.json
pyroclast/data/test.sql
pyroclast/data/test.unq
pyroclast/data/test.xlsx
pyroclast/data/test.xml
pyroclast/docs/__init__.py
pyroclast/docs/pyroclast.basic.html
pyroclast/docs/pyroclast.data.html
pyroclast/docs/pyroclast.dataTables.html
pyroclast/docs/pyroclast.docs.html
pyroclast/docs/pyroclast.html
pyroclast/docs/pyroclast.objectHierarchies.html
pyroclast/docs/pyroclast.server.html
pyroclast/docs/pyroclast.test.basic.html
pyroclast/docs/pyroclast.test.dataTables.html
pyroclast/docs/pyroclast.test.html
pyroclast/docs/pyroclast.test.objectHierarchies.html
pyroclast/test/__init__.py
pyroclast/test/basic.py
pyroclast/test/dataTables.py
pyroclast/test/objectHierarchies.py