Metadata-Version: 1.1
Name: pyroclast
Version: 1.0.1
Summary: Basic Python-based data server for exposing flat table and object hierarchy files via REST-ful queries
Home-page: https://github.com/Tythos/pyroclast
Author: Brian Kirkpatrick
Author-email: code@tythos.net
License: MIT
Keywords: rest server json csv sqlite unqlite excel xml
Platform: UNKNOWN
Classifier: Development Status :: 4 - Beta
Classifier: Environment :: Console
Classifier: Intended Audience :: Developers
Classifier: Intended Audience :: Information Technology
Classifier: Intended Audience :: Science/Research
Classifier: Intended Audience :: System Administrators
Classifier: License :: OSI Approved :: MIT License
Classifier: Operating System :: OS Independent
Classifier: Topic :: Database :: Database Engines/Servers
Classifier: Topic :: Internet :: WWW/HTTP
Classifier: Topic :: Scientific/Engineering :: Information Analysis
Classifier: Programming Language :: Python :: 2
